gwadmin/__init__.py
gwadmin/cli.py
gwadmin/config.py
gwadmin/watch/__init__.py
gwadmin/watch/clients/__init__.py
gwadmin/watch/clients/admin_client.py
gwadmin/watch/clients/constrained_mqtt_client.py
gwadmin/watch/clients/dac_client.py
gwadmin/watch/clients/relay_client.py
gwadmin/watch/relay_app.py
gwadmin/watch/relay_app.tcss
gwadmin/watch/widgets/__init__.py
gwadmin/watch/widgets/dac_widget_info.py
gwadmin/watch/widgets/dacs.py
gwadmin/watch/widgets/keepalive.py
gwadmin/watch/widgets/mqtt.py
gwadmin/watch/widgets/relay_state_text.py
gwadmin/watch/widgets/relay_toggle_button.py
gwadmin/watch/widgets/relay_widget_info.py
gwadmin/watch/widgets/relays.py
gwadmin/watch/widgets/time_input.py
gwadmin/watch/widgets/timer.py
gridworks_admin-1.2.1.dist-info/WHEEL
gridworks_admin-1.2.1.dist-info/entry_points.txt
gridworks_admin-1.2.1.dist-info/METADATA
gridworks_admin-1.2.1.dist-info/RECORD
