Metadata-Version: 2.3
Name: gridworks-admin
Version: 1.2.1
Summary: CLI tool for monitoring gridworks-scada devices.
Author: Andrew Schweitzer
Author-email: Andrew Schweitzer <schweitz72@gmail.com>
Requires-Dist: gridworks-proactor>=4.1.9
Requires-Dist: gridworks-scada-protocol>=1.2.1
Requires-Dist: numpy>=2.3.3
Requires-Dist: paho-mqtt>=2.1.0
Requires-Dist: pydantic>=2.11.9
Requires-Dist: python-dotenv>=1.1.1
Requires-Dist: result>=0.9.0
Requires-Dist: rich>=14.1.0
Requires-Dist: textual>=6.1.0
Requires-Dist: typer>=0.17.4
Requires-Python: >=3.11
